pbarticles/__init__.py
pbarticles/__main__.py
pbarticles/article_parser.py
pbarticles/downloader.py
pbarticles/pdf.py
pbarticles-0.3.dist-info/entry_points.txt
pbarticles-0.3.dist-info/LICENSE
pbarticles-0.3.dist-info/WHEEL
pbarticles-0.3.dist-info/METADATA
pbarticles-0.3.dist-info/RECORD
