Metadata-Version: 2.1
Name: pbarticles
Version: 0.3
Summary: A package to make a PDF from Pybites articles
Author-email: Bob Belderbos <bob@pybit.es>
Requires-Python: >=3.9
Classifier: License :: OSI Approved :: MIT License
Requires-Dist: fpdf2>=2.5.4
Requires-Dist: newspaper3k>=0.2.8
Requires-Dist: python-dateutil>=2.8.2
Requires-Dist: requests>=2.27.1
Requires-Dist: requests-cache>=0.9.4
Requires-Dist: requests-file>=1.5.1
Requires-Dist: typer>=0.4.1
Project-URL: Home, https://github.com/bbelderbos/pb_articles
